{
  "$schema": "https://developer.microsoft.com/json-schemas/fabric/item/report/definition/visualContainer/2.11.0/schema.json",
  "name": "v4holdscard",
  "position": {
    "x": 992,
    "y": 64,
    "z": 3000,
    "height": 100,
    "width": 272,
    "tabOrder": 3000
  },
  "visual": {
    "visualType": "card",
    "query": {
      "queryState": {
        "Values": {
          "projections": [
            {
              "field": {
                "Measure": {
                  "Expression": {
                    "SourceRef": {
                      "Entity": "_Measures"
                    }
                  },
                  "Property": "Active Holds"
                }
              },
              "queryRef": "_Measures.Active Holds",
              "nativeQueryRef": "Active Holds"
            }
          ]
        }
      }
    },
    "objects": {
      "labels": [
        {
          "properties": {}
        }
      ]
    }
  }
}